{"ocr_results":[{"text":"关于《反击》剧本，于会泳对“英雄人物不够高大”这条意见","box":[[2617,199],[4466,216],[4465,298],[2616,281]]},{"text":"（清华、北大《电影创作组》在炮制《反击》过程中，给迟","box":[[264,274],[2016,257],[2016,328],[264,345]]},{"text":"旁边特注明：“这个问题最重要，是关键性的问题。”","box":[[2476,326],[4107,318],[4108,408],[2476,415]]},{"text":"群、谢静宜写信请示一些问题），迟群的批语：","box":[[98,395],[1547,383],[1547,450],[98,462]]},{"text":"《反击》于九月间炮制出来以后，于会泳等连夜审看，一致称","box":[[2639,443],[4479,456],[4478,536],[2638,523]]},{"text":"“剧本我看了一遍，总的感觉曲折性不够，应体现胜利来之不","box":[[258,505],[2021,495],[2022,566],[259,575]]},{"text":"赞这部影片“大方向对头”，“有重大现实政治意义”。张春桥提","box":[[2479,572],[4482,568],[4483,652],[2479,655]]},{"text":"易。”","box":[[96,625],[267,615],[271,692],[101,701]]},{"text":"出暂不上映后，刘庆棠还说什么“现在不上，是要等到适当的时机","box":[[2483,693],[4484,689],[4484,771],[2483,775]]},{"text":"“全国已点名，问题不大。”","box":[[253,741],[1056,737],[1056,801],[253,805]]},{"text":"再上”，“好钢要用在刀刃上”","box":[[2475,816],[3825,800],[3826,882],[2476,898]]},{"text":"“罢官撤职、关起来一一这是走资派对革命派的一贯手段，不","box":[[253,858],[2020,851],[2020,914],[253,922]]},{"text":"欢共王#．调大出发个学","box":[[2468,945],[3248,923],[3250,994],[2470,1015]]},{"text":"文化部批判于会泳大会发言#（","box":[[3269,939],[4462,935],[4462,992],[3270,996]]},{"text":"奇怪。”","box":[[92,972],[426,968],[427,1039],[93,1043]]},{"text":"（张春桥1976年9月发出黑指示）：“影片（《反击》）不同","box":[[2658,1065],[4481,1061],[4481,1130],[2659,1134]]},{"text":"“要害是被撤。至于本人态度当然是不会接受的，是要斗","box":[[240,1089],[2018,1087],[2018,1151],[240,1153]]},{"text":"于一般反映文化大革命的作品，不要急于在国庆节期间放映，可以","box":[[2485,1188],[4481,1184],[4481,1255],[2485,1259]]},{"text":"的。”贵年个","box":[[94,1212],[561,1212],[561,1270],[94,1270]]},{"text":"继续翻拷贝。”“要选择一个适当的时机拿出去。”","box":[[2476,1307],[4462,1294],[4462,1376],[2476,1389]]},{"text":"出“人和人的关系从来就是政治的关系、：阶级的关系。”一","box":[[81,1328],[2003,1320],[2003,1383],[81,1391]]},{"text":"九###","box":[[4088,1417],[4463,1423],[4461,1494],[4087,1487]]},{"text":"#风#大####","box":[[2472,1438],[3376,1424],[3377,1488],[2473,1501]]},{"text":"《北京日报》1976年12月11日","box":[[3347,1430],[4010,1430],[4010,1480],[3347,1480]]},{"text":"本志同早美路省","box":[[129,1445],[790,1441],[790,1499],[129,1503]]},{"text":"摘自文化部有关“四人帮”及其亲信的罪行材料","box":[[836,1443],[1916,1443],[1916,1493],[836,1493]]},{"text":"迟群关于《反击》的批语：“《反击》在走资派那里，已成了","box":[[216,1564],[2014,1564],[2014,1626],[216,1626]]},{"text":"毛主席逝世后，大约九月十八日前后，清华政治部领导人××","box":[[2476,1559],[4455,1555],[4455,1618],[2476,1622]]},{"text":"强级地震。政治上思想上路线上的正确和艺术上的完美，二者统","box":[[89,1680],[2018,1681],[2018,1745],[89,1743]]},{"text":"x说：“（《反击》后）第二部电影要一直写到毛主席去世，对","box":[[2485,1681],[4466,1681],[4466,1745],[2485,1745]]},{"text":"一，是赶走资产阶级老爷的保证。”","box":[[94,1803],[1113,1801],[1113,1858],[94,1860]]},{"text":"毛主席遗志是继承还是背叛。”创作组表示有生活，×说：，“过","box":[[2485,1806],[4471,1799],[4471,1862],[2485,1870]]},{"text":"摘自文化部有关“四人帮”及其亲信的罪行材料","box":[[833,1922],[1922,1922],[1922,1966],[833,1966]]},{"text":"安","box":[[1907,1924],[2010,1924],[2010,1970],[1907,1970]]},{"text":"两周也许能够给你们讲一讲，现在还看不清楚。”。人寻一为","box":[[2475,1918],[4473,1901],[4473,1987],[2476,2004]]},{"text":"1976年8月中、下旬一个晚上，《反击》在河南摄制期间，迟","box":[[201,2039],[2014,2039],[2014,2100],[201,2100]]},{"text":"摘自文化部有关“四人帮”及其亲信的罪行材料","box":[[3279,2045],[4384,2035],[4385,2091],[3279,2101]]},{"text":"群跟我（荣泳霖一——清华党委副书记）讲：“《反击》对走资派来","box":[[79,2151],[2014,2151],[2014,2220],[79,2220]]},{"text":"1976年，毛主席逝世后，约十七、十八日，迟群说：“我就喜","box":[[2616,2166],[4482,2160],[4483,2236],[2616,2242]]},{"text":"讲，好比一次大地震，成了洪水猛兽。不是走资派怕什么呢？”","box":[[78,2268],[1990,2270],[1990,2341],[78,2339]]},{"text":"欢认准了干到底的人。原来不是讲“继续跟走资派斗下去，不怕上","box":[[2481,2290],[4480,2285],[4481,2361],[2481,2367]]},{"text":"“越是这样越要搞下去，继续笑出跟走资派斗，这是一个历史时期","box":[[98,2385],[2014,2395],[2014,2464],[98,2454]]},{"text":"山打游击吗？现在更清楚了：按既定方针办，跟走资派斗下去。电","box":[[2483,2411],[4480,2404],[4481,2484],[2483,2492]]},{"text":"的主题。要说艺术，我们一窍不通，但《反击》还有出来就起到","box":[[80,2506],[2012,2518],[2012,2581],[79,2570]]},{"text":"影不反映这个反映什么？这次可以搞得更充裕一些，更深一些，把","box":[[2485,2534],[4482,2525],[4483,2601],[2485,2611]]},{"text":"了“反击”的作用，就是抓住了这一条。”","box":[[80,2614],[1531,2641],[1530,2712],[79,2685]]},{"text":"《反击》的缺点弥补过来。”","box":[[2505,2665],[3362,2661],[3362,2730],[2505,2734]]},{"text":"摘自文化部有关“四人帮”及其亲信的罪行材料","box":[[827,2750],[1913,2758],[1912,2810],[827,2802]]},{"text":"摘自文化部有关“四人帮”及其亲信的罪行材料","box":[[3279,2786],[4381,2772],[4381,2825],[3279,2838]]},{"text":"1976年4、5月间于会泳两次向电影局和北影的有关同志提出","box":[[205,2871],[2011,2892],[2010,2961],[205,2940]]},{"text":"1976年9月26日，清华党委副书记荣泳霖、北大党委副书记魏","box":[[2616,2912],[4486,2897],[4486,2966],[2616,2981]]},{"text":"要把《反击》的剧本“抓好”，一再强调《反击》“题村重大”，","box":[[84,2985],[1974,3015],[1973,3084],[83,3053]]},{"text":"银秋去北影看《反击》。在回来的汽车上，我们（创作组同志对写","box":[[2483,3032],[4489,3014],[4490,3095],[2484,3112]]},{"text":"“有很大政治意义”","box":[[112,3100],[672,3112],[671,3177],[110,3165]]},{"text":"第二部电影）表示：对当前斗爭不了解，很难写。荣说：“就是写","box":[[2479,3151],[4500,3128],[4501,3215],[2480,3238]]},{"text":"106","box":[[137,3220],[247,3220],[247,3283],[137,3283]]},{"text":"107","box":[[4320,3264],[4436,3264],[4436,3329],[4320,3329]]}],"dimensions":{"height":3456,"width":4608}}